pynimbus/__init__.py
pynimbus/checks.py
pynimbus/nhcoutlooks.py
pynimbus/pynimbus.py
pynimbus/spcreports.py
PyNimbus-0.0.2.dist-info/LICENSE.md
PyNimbus-0.0.2.dist-info/METADATA
PyNimbus-0.0.2.dist-info/WHEEL
PyNimbus-0.0.2.dist-info/top_level.txt
PyNimbus-0.0.2.dist-info/zip-safe
PyNimbus-0.0.2.dist-info/RECORD
