Metadata-Version: 2.1
Name: PyNimbus
Version: 0.0.2
Summary: A Python package to organize National Weather Service product data.
Home-page: https://github.com/WxBDM/PyNimbus
Author: Brandon Molyneaux
Author-email: bdmolyne@gmail.com
License: BSD 3-clause "New" or "Revised License"
Keywords: meteorology weather
Platform: UNKNOWN
Classifier: License :: OSI Approved :: BSD License
Classifier: Programming Language :: Python :: 3
Classifier: Programming Language :: Python :: 3.7
Requires-Dist: pandas (>=0.23.4)
